clear_eval/__init__.py
clear_eval/analysis_runner.py
clear_eval/args.py
clear_eval/cli.py
clear_eval/load_ui.py
clear_eval/logging_config.py
clear_eval/dashboard/__init__.py
clear_eval/dashboard/show_analysis_dashboard.py
clear_eval/pipeline/EvalUseCase.py
clear_eval/pipeline/__init__.py
clear_eval/pipeline/caching_utils.py
clear_eval/pipeline/config_loader.py
clear_eval/pipeline/constants.py
clear_eval/pipeline/eval_utils.py
clear_eval/pipeline/evaluation_criteria.py
clear_eval/pipeline/full_pipeline.py
clear_eval/pipeline/llm_chat_utils.py
clear_eval/pipeline/propmts.py
clear_eval/pipeline/threading_utils.py
clear_eval/pipeline/setup/__init__.py
clear_eval/pipeline/setup/default_config.yaml
clear_eval/sample_data/__init__.py
clear_eval/sample_data/gsm8k/__init__.py
clear_eval/sample_data/gsm8k/analysis_results_gsm8k_default.zip
clear_eval/sample_data/gsm8k/gsm8k_default_predictions.csv
clear_eval-1.0.8.dist-info/licenses/LICENSE
clear_eval-1.0.8.dist-info/METADATA
clear_eval-1.0.8.dist-info/WHEEL
clear_eval-1.0.8.dist-info/entry_points.txt
clear_eval-1.0.8.dist-info/top_level.txt
clear_eval-1.0.8.dist-info/RECORD
