Metadata-Version: 2.4
Name: clear_eval
Version: 1.0.8
Summary: A python API sdk facilitating Error Analysis via LLM-as-a-Judge
Author-email: Lilach Eden <lilache@il.ibm.com>, Asaf Yehudai <asaf.yehudai@ibm.com>
License: Apache-2.0
Classifier: Programming Language :: Python :: 3
Classifier: Operating System :: OS Independent
Requires-Python: >=3.10
License-File: LICENSE
Requires-Dist: python-dotenv
Requires-Dist: langchain
Requires-Dist: langgraph
Requires-Dist: langchain_openai
Requires-Dist: langchain_ibm
Requires-Dist: ibm_watsonx_ai>=1.2.8
Requires-Dist: openai
Requires-Dist: pyyaml
Requires-Dist: pandas
Requires-Dist: tqdm
Requires-Dist: pyyaml
Requires-Dist: streamlit
Requires-Dist: matplotlib
Requires-Dist: seaborn
Requires-Dist: langchain_community
Requires-Dist: numpy
Requires-Dist: pyarrow>=15.0.0
Dynamic: license-file
